{
  "enableSearch": true,
  "pages": [
    {
      "headings": {
        "tell-don-t-ask": "Tell, Don't Ask",
        "": ""
      },
      "pageNav": 2,
      "header": "header.md",
      "footer": "footer.md",
      "siteNav": "site-nav.md",
      "src": "contents/textbook/lecture01/tellNotAskAndPrivateAccessModifiersSummary/index.md",
      "title": "",
      "layout": "default"
    },
    {
      "headings": {
        "cs2030-programming-methodology-ii": "CS2030: Programming Methodology II"
      },
      "header": "header.md",
      "footer": "footer.md",
      "pageNav": 2,
      "siteNav": "site-nav.md",
      "src": "index.md",
      "title": "",
      "layout": "default"
    },
    {
      "headings": {
        "cs2030-ay2019-2020-semester-2": "CS2030 AY2019/2020 Semester 2",
        "setting-up-staging-env": "Setting Up Staging Env"
      },
      "src": "README.md",
      "title": "",
      "layout": "default"
    },
    {
      "headings": {
        "for-windows-users": "For Windows Users",
        "for-macos-users": "For MacOS Users",
        "setting-up-java": "Setting Up Java"
      },
      "pageNav": 2,
      "header": "header.md",
      "footer": "footer.md",
      "siteNav": "site-nav.md",
      "src": "contents/guides/settingUpJava.md",
      "title": "",
      "layout": "default"
    },
    {
      "headings": {
        "setting-up-windows-subsystem-for-linux-wsl": "Setting Up Windows Subsystem for Linux (WSL)",
        "downloading-xming-for-gvim": "Downloading XMing for gVim",
        "downloading-and-setting-up-ubuntu": "Downloading and Setting Up Ubuntu",
        "setting-up-your-vimrc-file": "Setting up your .vimrc file",
        "setting-up-lab-environment": "Setting Up Lab Environment"
      },
      "pageNav": 2,
      "header": "header.md",
      "footer": "footer.md",
      "siteNav": "site-nav.md",
      "src": "contents/guides/settingUpLabEnv.md",
      "title": "",
      "layout": "default"
    },
    {
      "headings": {
        "setting-up-macvim": "Setting Up MacVim"
      },
      "pageNav": 2,
      "header": "header.md",
      "footer": "footer.md",
      "siteNav": "site-nav.md",
      "src": "contents/guides/settingUpMacVim.md",
      "title": "",
      "layout": "default"
    },
    {
      "headings": {
        "setting-up-vim": "Setting Up Vim"
      },
      "pageNav": 2,
      "header": "header.md",
      "footer": "footer.md",
      "siteNav": "site-nav.md",
      "src": "contents/guides/settingUpVim.md",
      "title": "",
      "layout": "default"
    },
    {
      "headings": {
        "what-do-i-do-here": "What do I do here?",
        "how-can-i-contribute": "How can I contribute?",
        "peer-learning-segment": "Peer Learning Segment"
      },
      "pageNav": 2,
      "header": "header.md",
      "footer": "footer.md",
      "siteNav": "site-nav.md",
      "src": "contents/peerlearning/peerlearning.md",
      "title": "",
      "layout": "default"
    },
    {
      "headings": {
        "task-creation": "Task Creation",
        "think-of-the-problem-statement": "Think of the Problem Statement",
        "creating-the-solution": "Creating the Solution",
        "creating-test-input-output-files": "Creating Test Input/Output Files",
        "preparing-your-files-for-upload": "Preparing Your Files for Upload",
        "upload-to-codecrunch": "Upload to CodeCrunch",
        "test-your-task": "Test your Task",
        "final-step": "Final Step!",
        "peer-learning-task-creation-using-codecrunch": "Peer Learning Task Creation using Codecrunch"
      },
      "pageNav": 2,
      "header": "header.md",
      "footer": "footer.md",
      "siteNav": "site-nav.md",
      "src": "contents/peerlearning/peerlearningtask.md",
      "title": "",
      "layout": "default"
    },
    {
      "headings": {
        "how-do-i-contribute": "How Do I Contribute?",
        "piazza-participation": "Piazza Participation"
      },
      "pageNav": 2,
      "header": "header.md",
      "footer": "footer.md",
      "siteNav": "site-nav.md",
      "src": "contents/peerlearning/piazza.md",
      "title": "",
      "layout": "default"
    },
    {
      "headings": {
        "step-0-signing-up-for-github": "Step 0: Signing Up for Github",
        "step-1-adding-an-issue-to-the-repository": "Step 1: Adding an Issue to the repository",
        "step-2-searching-for-issues-to-the-repository": "Step 2: Searching For Issues to the Repository",
        "step-3-finding-the-section-to-edit": "Step 3: Finding the section to edit",
        "step-4-forking-the-repository": "Step 4: Forking the Repository",
        "step-5-editing-using-the-markdown-editor": "Step 5: Editing using the Markdown editor",
        "step-6-save-your-file-changes": "Step 6: Save your file changes",
        "step-7-create-your-pull-request": "Step 7: Create your Pull Request",
        "step-8-view-your-website-changes": "Step 8: View your website changes",
        "step-9-fixing-merge-conflicts": "Step 9: Fixing Merge Conflicts",
        "textbook-contributions": "Textbook Contributions"
      },
      "pageNav": 2,
      "header": "header.md",
      "footer": "footer.md",
      "siteNav": "site-nav.md",
      "src": "contents/peerlearning/textbook.md",
      "title": "",
      "layout": "default"
    },
    {
      "headings": {
        "abstraction": "Abstraction",
        "": "",
        "-2": ""
      },
      "pageNav": 2,
      "header": "header.md",
      "footer": "footer.md",
      "siteNav": "site-nav.md",
      "src": "contents/textbook/lecture01/abstraction/abstraction.md",
      "title": "",
      "layout": "default"
    },
    {
      "headings": {
        "abstraction-vs-encapsulation": "Abstraction Vs Encapsulation",
        "abstraction": "Abstraction",
        "encapsulation": "Encapsulation",
        "example-the-student-class": "Example: The Student class"
      },
      "pageNav": 2,
      "header": "header.md",
      "footer": "footer.md",
      "siteNav": "site-nav.md",
      "src": "contents/textbook/lecture01/abstractionVsEncapsulation/abstractionVsEncapsulation.md",
      "title": "",
      "layout": "default"
    },
    {
      "headings": {},
      "src": "contents/textbook/lecture01/imperativeProgramming/definition.md",
      "title": "",
      "layout": "default"
    },
    {
      "headings": {},
      "src": "contents/textbook/lecture01/imperativeProgramming/examples.md",
      "title": "",
      "layout": "default"
    },
    {
      "headings": {},
      "src": "contents/textbook/lecture01/imperativeProgramming/exercises.md",
      "title": "",
      "layout": "default"
    },
    {
      "headings": {},
      "src": "contents/textbook/lecture01/imperativeProgramming/explanation.md",
      "title": "",
      "layout": "default"
    },
    {
      "headings": {
        "introduction-to-imperative-programming": "Introduction to Imperative Programming",
        "exercises": "Exercises",
        "additional-resources": "Additional Resources"
      },
      "pageNav": 2,
      "header": "header.md",
      "footer": "footer.md",
      "siteNav": "site-nav.md",
      "src": "contents/textbook/lecture01/imperativeProgramming/imperativeProgramming.md",
      "title": "",
      "layout": "default"
    },
    {
      "headings": {},
      "src": "contents/textbook/lecture01/imperativeProgramming/references.md",
      "title": "",
      "layout": "default"
    },
    {
      "headings": {},
      "src": "contents/textbook/lecture01/imperativeProgramming/resources.md",
      "title": "",
      "layout": "default"
    },
    {
      "headings": {
        "lecture-1": "Lecture 1",
        "textbook": "Textbook"
      },
      "pageNav": 2,
      "header": "header.md",
      "footer": "footer.md",
      "siteNav": "site-nav.md",
      "src": "contents/textbook/textbook.md",
      "title": "",
      "layout": "default"
    }
  ]
}
